glueplate/__init__.py
glueplate/config/__init__.py
glueplate-1.1.0.dist-info/LICENSE
glueplate-1.1.0.dist-info/METADATA
glueplate-1.1.0.dist-info/WHEEL
glueplate-1.1.0.dist-info/top_level.txt
glueplate-1.1.0.dist-info/RECORD
