Metadata-Version: 2.1
Name: glueplate
Version: 1.1.0
Summary: Settings framework for framework or library.
Home-page: https://github.com/tsuyukimakoto/glueplate
Author: makoto tsuyuki
Author-email: mtsuyuki@gmail.com
License: MIT
Keywords: settings config framework
Platform: UNKNOWN
Classifier: Intended Audience :: Developers
Classifier: License :: OSI Approved :: MIT License
Classifier: Operating System :: POSIX
Classifier: Programming Language :: Python :: 3.5
Classifier: Programming Language :: Python :: 3.6
Classifier: Programming Language :: Python :: 3.7
Classifier: Programming Language :: Python :: 3.8
Classifier: Programming Language :: Python :: Implementation :: PyPy
Classifier: Topic :: Software Development :: Libraries
Classifier: Topic :: Software Development :: Libraries :: Application Frameworks
Classifier: Topic :: Software Development :: Libraries :: Python Modules
